{
  "lastReviewed": "April 2026",
  "products": [
    {
      "id": "blueforge",
      "name": "blueForge",
      "description": "Desktop AI development environment — verification-first; the coding tool that runs the test, not just the model.",
      "logo": "/assets/logos/blueforge.svg",
      "status": "active"
    },
    {
      "id": "linda",
      "name": "Linda",
      "description": "askLinda.",
      "logo": "/assets/logos/linda.svg",
      "status": "active"
    },
    {
      "id": "isthisascam",
      "name": "isThisAScam",
      "description": "Scam detection.",
      "logo": "/assets/logos/isthisascam.svg",
      "status": "active"
    },
    {
      "id": "whatdoesmyleasesay",
      "name": "whatDoesMyLeaseSay",
      "description": "Lease intelligence.",
      "logo": "/assets/logos/whatdoesmyleasesay.svg",
      "status": "active"
    },
    {
      "id": "fixmyemail",
      "name": "fixMyEmail",
      "description": "Email composition aid.",
      "logo": "/assets/logos/fixmyemail.svg",
      "status": "active"
    },
    {
      "id": "reviewmycontract",
      "name": "reviewMyContract",
      "description": "Contract review.",
      "logo": "/assets/logos/reviewmycontract.svg",
      "status": "active"
    },
    {
      "id": "slumbernet",
      "name": "slumberNet",
      "description": "Distributed verification mesh substrate.",
      "logo": "/assets/logos/slumbernet.svg",
      "status": "dev"
    },
    {
      "id": "blueglued",
      "name": "blueGlued",
      "description": "Consumer device intelligence mesh.",
      "logo": "/assets/logos/blueglued.svg",
      "status": "dev"
    },
    {
      "id": "forgelegal",
      "name": "forgeLegal",
      "description": "Legal-vertical forge variant.",
      "logo": "/assets/logos/forgelegal.svg",
      "status": "dev"
    },
    {
      "id": "forgemedical",
      "name": "forgeMedical",
      "description": "Medical-vertical forge variant.",
      "logo": "/assets/logos/forgemedical.svg",
      "status": "dev"
    },
    {
      "id": "forgefinancial",
      "name": "forgeFinancial",
      "description": "Financial-vertical forge variant.",
      "logo": "/assets/logos/forgefinancial.svg",
      "status": "dev"
    },
    {
      "id": "forgejunior",
      "name": "forgeJunior",
      "description": "Junior-developer-focused forge variant (spec stage).",
      "logo": "/assets/logos/forgejunior.svg",
      "status": "dev"
    },
    {
      "id": "faustindex",
      "name": "faustIndex",
      "description": "AI reliability standard.",
      "logo": "/assets/logos/faustindex.svg",
      "status": "dev"
    },
    {
      "id": "truthlayer",
      "name": "truthLayer",
      "description": "Developer middleware for verified AI outputs.",
      "logo": "/assets/logos/truthlayer.svg",
      "status": "dev"
    }
  ]
}
